sqlfluffrs/__init__.py
sqlfluffrs/__init__.pyi
sqlfluffrs/py.typed
sqlfluffrs/sqlfluffrs.pypy310-pp73-arm-linux-gnu.so
sqlfluffrs-4.0.0.dist-info/METADATA
sqlfluffrs-4.0.0.dist-info/WHEEL
sqlfluffrs-4.0.0.dist-info/licenses/LICENSE.md
sqlfluffrs.libs/libgcc_s-262c4f60.so.1
sqlfluffrs-4.0.0.dist-info/RECORD
