Metadata-Version: 2.4
Name: sqlfluffrs
Version: 4.0.0
Classifier: Development Status :: 3 - Alpha
Classifier: Environment :: Console
Classifier: Intended Audience :: Developers
Classifier: License :: OSI Approved :: MIT License
Classifier: Operating System :: Unix
Classifier: Operating System :: POSIX
Classifier: Operating System :: MacOS
Classifier: Operating System :: Microsoft :: Windows
Classifier: Programming Language :: Rust
Classifier: Programming Language :: Python
Classifier: Programming Language :: Python :: 3
Classifier: Programming Language :: Python :: 3.9
Classifier: Programming Language :: Python :: 3.10
Classifier: Programming Language :: Python :: 3.11
Classifier: Programming Language :: Python :: 3.12
Classifier: Programming Language :: Python :: 3.13
Classifier: Programming Language :: Python :: Implementation :: CPython
Classifier: Programming Language :: Python :: Implementation :: PyPy
Classifier: Programming Language :: SQL
Classifier: Topic :: Utilities
Classifier: Topic :: Software Development :: Quality Assurance
License-File: LICENSE.md
Summary: The SQL Linter for Humans
Requires-Python: >=3.9
Project-URL: Documentation, https://docs.sqlfluff.com
Project-URL: Homepage, https://www.sqlfluff.com
Project-URL: Issue Tracker, https://github.com/sqlfluff/sqlfluff/issues
Project-URL: Source, https://github.com/sqlfluff/sqlfluff
